LICENSE
MANIFEST.in
README.rst
setup.py
wagtailcolourpicker/__init__.py
wagtailcolourpicker/conf.py
wagtailcolourpicker/forms.py
wagtailcolourpicker/models.py
wagtailcolourpicker/urls.py
wagtailcolourpicker/views.py
wagtailcolourpicker/wagtail_hooks.py
wagtailcolourpicker.egg-info/PKG-INFO
wagtailcolourpicker.egg-info/SOURCES.txt
wagtailcolourpicker.egg-info/dependency_links.txt
wagtailcolourpicker.egg-info/requires.txt
wagtailcolourpicker.egg-info/top_level.txt
wagtailcolourpicker/static/colourpicker/css/colourpicker.css
wagtailcolourpicker/static/colourpicker/js/chooser.js
wagtailcolourpicker/static/colourpicker/js/colourpicker.js
wagtailcolourpicker/templates/colourpicker/chooser/chooser.html
wagtailcolourpicker/templates/colourpicker/chooser/chosen.js
wagtailcolourpicker/templates/colourpicker/forms/widgets/colour_option.html
wagtailcolourpicker/utils/__init__.py
wagtailcolourpicker/utils/colour.py
wagtailcolourpicker/utils/version.py