Metadata-Version: 2.1
Name: wagtailcolourpicker
Version: 0.0.6
Summary: Wagtail text colour picker for DraftJS
Home-page: https://github.com/AccentDesign/wagtailcolourpicker/
Author: Stuart George
Author-email: stuart@accentdesign.co.uk
License: MIT
Download-URL: https://pypi.python.org/pypi/wagtailcolourpicker
Keywords: wagtail,draftjs,colour,picker,accent,design
Platform: UNKNOWN
Classifier: Development Status :: 3 - Alpha
Classifier: Intended Audience :: Developers
Classifier: License :: OSI Approved :: MIT License
Classifier: Operating System :: OS Independent
Classifier: Programming Language :: Python :: 3
Classifier: Programming Language :: Python :: 3.4
Classifier: Programming Language :: Python :: 3.5
Classifier: Programming Language :: Python :: 3.6
Classifier: Framework :: Django
Classifier: Framework :: Django :: 2.0
Classifier: Framework :: Wagtail
Classifier: Framework :: Wagtail :: 2
Classifier: Topic :: Internet :: WWW/HTTP :: Site Management
Provides-Extra: docs
